README.rst
setup.py
Flask_SACore.egg-info/PKG-INFO
Flask_SACore.egg-info/SOURCES.txt
Flask_SACore.egg-info/dependency_links.txt
Flask_SACore.egg-info/not-zip-safe
Flask_SACore.egg-info/requires.txt
Flask_SACore.egg-info/top_level.txt
flask_sacore/__init__.py