Metadata-Version: 1.1
Name: Flask-SACore
Version: 0.0.1
Summary: SQLAlchemy Core extension for Flask
Home-page: https://github.com/jjmurre/flask-sacore
Author: Jan Murre
Author-email: jan.murre@catalyz.nl
License: MIT
Platform: any
Classifier: Environment :: Web Environment
Classifier: Intended Audience :: Developers
Classifier: License :: OSI Approved :: MIT License
Classifier: Operating System :: OS Independent
Classifier: Programming Language :: Python :: 2.7
Classifier: Programming Language :: Python :: 3.4
Classifier: Programming Language :: Python :: 3.5
Classifier: Topic :: Software Development :: Libraries :: Python Modules
